propshop/__init__.py
propshop/api.py
propshop/configs.py
propshop/defaults.toml
propshop/library.py
propshop-0.1.3.dist-info/LICENSE
propshop-0.1.3.dist-info/WHEEL
propshop-0.1.3.dist-info/METADATA
propshop-0.1.3.dist-info/RECORD
